touchscroller/__init__.py
touchscroller-0.1.2.dist-info/licenses/LICENSE
touchscroller-0.1.2.dist-info/METADATA
touchscroller-0.1.2.dist-info/WHEEL
touchscroller-0.1.2.dist-info/top_level.txt
touchscroller-0.1.2.dist-info/RECORD
