Metadata-Version: 2.4
Name: touchscroller
Version: 0.1.2
Summary: Simulate multi-touch scrolling using uinput
Author: Mirko Kunze
License: MIT
Project-URL: Homepage, https://github.com/mqnc/touchscroller
Requires-Python: >=3.7
License-File: LICENSE
Requires-Dist: python-uinput
Dynamic: license-file
